tests/__init__.py
uniqchars_pac/__init__.py
uniqchars_pac/main.py
uniqchars_pac/app/__init__.py
uniqchars_pac/app/app.py
uniqchars_pac/utils/__init__.py
uniqchars_pac/utils/exceptions.py
uniqchars_pac/utils/functions.py
uniqchars_pac-2.0.dist-info/LICENSE
uniqchars_pac-2.0.dist-info/METADATA
uniqchars_pac-2.0.dist-info/WHEEL
uniqchars_pac-2.0.dist-info/entry_points.txt
uniqchars_pac-2.0.dist-info/top_level.txt
uniqchars_pac-2.0.dist-info/RECORD
